pysvgexport/__init__.py
pysvgexport/__main__.py
pysvgexport/js_function.py
pysvgexport/script.py
pysvgexport/svg_export.py
pysvgexport-1.2.2.dist-info/LICENSE
pysvgexport-1.2.2.dist-info/METADATA
pysvgexport-1.2.2.dist-info/WHEEL
pysvgexport-1.2.2.dist-info/entry_points.txt
pysvgexport-1.2.2.dist-info/top_level.txt
pysvgexport-1.2.2.dist-info/RECORD
