Metadata-Version: 2.1
Name: pysvgexport
Version: 1.2.2
Summary: A package for exporting svg format
Home-page: https://github.com/vantrong291/pysvgexport
Author: vantrong291
Author-email: vantrong291@gmail.com
License: UNKNOWN
Platform: UNKNOWN
Classifier: Programming Language :: Python :: 3
Classifier: License :: OSI Approved :: MIT License
Classifier: Operating System :: OS Independent
Requires-Python: >=3.6
License-File: LICENSE
Requires-Dist: pyppeteer
Requires-Dist: Pillow
